conductor_celery/__init__.py
conductor_celery/tasks.py
conductor_celery/utils.py
conductor_celery/wrapper.py
conductor_celery-0.1.9.dist-info/LICENSE
conductor_celery-0.1.9.dist-info/METADATA
conductor_celery-0.1.9.dist-info/WHEEL
conductor_celery-0.1.9.dist-info/RECORD
