Metadata-Version: 2.1
Name: conductor_celery
Version: 0.1.9
Summary: This is a template repository for Python projects that use Poetry for their dependency management.
Home-page: https://github.com/tomas_correa/conductor-celery
Author: Tomas Correa
Author-email: ftomas.correa@gmail.com
Requires-Python: >=3.8,<4.0
Classifier: Programming Language :: Python :: 3
Classifier: Programming Language :: Python :: 3.8
Classifier: Programming Language :: Python :: 3.9
Classifier: Programming Language :: Python :: 3.10
Classifier: Programming Language :: Python :: 3.11
Classifier: Programming Language :: Python :: 3.12
Requires-Dist: celery (>=5.3.1,<6.0.0)
Requires-Dist: conductor-python (==1.0.71)
Project-URL: Documentation, https://tomas_correa.github.io/conductor-celery/
Project-URL: Repository, https://github.com/tomas_correa/conductor-celery
